[
  {
    "id": "3pm",
    "short": "3ème Prépa Métiers",
    "full": "3ème Prépa Métiers",
    "niveau": "3eme",
    "filiere": "maintenance",
    "effectif": 24,
    "annee": "3ème",
    "couleur": "#6366f1",
    "description": "Découverte des métiers et renforcement des bases en maths et sciences.",
    "resources": {
      "maths": {
        "cours": [
          { "id": 1, "titre": "Proportionnalité et pourcentages", "type": "Cours", "desc": "Cours complet + exemples du quotidien", "url": "#", "date": "12/09/2025" },
          { "id": 2, "titre": "Géométrie plane et aires", "type": "Cours", "desc": "Triangles, cercles, quadrilatères", "url": "#", "date": "03/10/2025" }
        ],
        "exercices": [
          { "id": 3, "titre": "TD 1 - Proportionnalité", "type": "Exercices", "desc": "12 exercices corrigés", "url": "#", "date": "15/09/2025" },
          { "id": 4, "titre": "Exercices types brevet", "type": "Exercices", "desc": "Série d'entraînement", "url": "#", "date": "20/11/2025" }
        ],
        "fiches": [
          { "id": 5, "titre": "Fiche révision - Calculs numériques", "type": "Fiche", "desc": "Priorités opératoires et puissances", "url": "#", "date": "08/01/2026" }
        ],
        "qcm": [],
        "tp": []
      },
      "sciences": { "cours": [], "exercices": [], "fiches": [], "qcm": [], "tp": [] }
    }
  },
  {
    "id": "cap1-rics",
    "short": "Seconde CAP RICS",
    "full": "CAP RICS - 1ère année (Réalisation Industrielle Chaudronnerie Soudure)",
    "niveau": "cap",
    "filiere": "chaudronnerie",
    "effectif": 12,
    "annee": "Seconde CAP",
    "couleur": "#f59e0b",
    "description": "Chaudronnerie et soudure : calculs d'aires, volumes, développés.",
    "resources": {
      "maths": {
        "cours": [
          { "id": 1001, "titre": "Développés de surfaces - Cylindre et cône", "type": "Cours", "desc": "Méthode de traçage et calculs", "url": "#", "date": "22/09/2025" },
          { "id": 1002, "titre": "Trigonométrie pour le chaudronnier", "type": "Cours", "desc": "Angles, sinus, cosinus en atelier", "url": "#", "date": "14/10/2025" }
        ],
        "exercices": [
          { "id": 1003, "titre": "TD Développés et traçage", "type": "Exercices", "desc": "10 exercices corrigés", "url": "#", "date": "06/10/2025" },
          { "id": 1004, "titre": "Calculs de masse et volume des métaux", "type": "Exercices", "desc": "Application directe atelier", "url": "#", "date": "18/11/2025" }
        ],
        "fiches": [
          { "id": 1005, "titre": "Formulaire Chaudronnerie", "type": "Fiche", "desc": "Aires, volumes, longueurs développées", "url": "#", "date": "12/01/2026" }
        ],
        "qcm": [
          { "id": 1006, "titre": "Quiz - Trigonométrie CAP", "type": "QCM", "desc": "15 questions interactives", "url": "#", "date": "20/01/2026" }
        ],
        "tp": []
      },
      "sciences": { "cours": [], "exercices": [], "fiches": [], "qcm": [], "tp": [] }
    }
  },
  {
    "id": "cap2-rics",
    "short": "Terminale CAP RICS",
    "full": "CAP RICS - 2ème année (Réalisation Industrielle Chaudronnerie Soudure)",
    "niveau": "cap",
    "filiere": "chaudronnerie",
    "effectif": 12,
    "annee": "Terminale CAP",
    "couleur": "#f59e0b",
    "description": "Approfondissement : résistance des matériaux, calculs de structures.",
    "resources": {
      "maths": {
        "cours": [
          { "id": 20, "titre": "Notions de résistance des matériaux", "type": "Cours", "desc": "Contrainte, section, allongement", "url": "#", "date": "09/09/2025" }
        ],
        "exercices": [
          { "id": 21, "titre": "TD RDM - Dimensionnement simple", "type": "Exercices", "desc": "8 exercices + corrigés", "url": "#", "date": "17/10/2025" }
        ],
        "fiches": [
          { "id": 22, "titre": "Tableau des sections courantes", "type": "Fiche", "desc": "Aide-mémoire rapide", "url": "#", "date": "05/01/2026" }
        ],
        "qcm": [],
        "tp": []
      },
      "sciences": { "cours": [], "exercices": [], "fiches": [], "qcm": [], "tp": [] }
    }
  },
  {
    "id": "2mmv",
    "short": "Seconde MMV",
    "full": "Seconde Bac Pro - Maintenance des Matériels et Véhicules",
    "niveau": "seconde",
    "filiere": "maintenance",
    "effectif": 20,
    "annee": "Seconde",
    "couleur": "#10b981",
    "description": "Bases maths/sciences pour la maintenance automobile et engins.",
    "resources": {
      "maths": {
        "cours": [
          { "id": 30, "titre": "Fonctions et vitesses de rotation", "type": "Cours", "desc": "Relation vitesse / couple / puissance", "url": "#", "date": "11/09/2025" },
          { "id": 31, "titre": "Électricité automobile - Bases", "type": "Cours", "desc": "Tension, intensité, résistance (loi d'Ohm)", "url": "#", "date": "25/09/2025" }
        ],
        "exercices": [
          { "id": 32, "titre": "TD Mécanique - Rapport de transmission", "type": "Exercices", "desc": "14 exercices corrigés", "url": "#", "date": "03/10/2025" }
        ],
        "fiches": [
          { "id": 33, "titre": "Fiche - Unités et conversions", "type": "Fiche", "desc": "SI et unités courantes en mécanique", "url": "#", "date": "14/01/2026" }
        ],
        "qcm": [
          { "id": 34, "titre": "QCM Électricité auto", "type": "QCM", "desc": "20 questions", "url": "#", "date": "22/01/2026" }
        ],
        "tp": []
      },
      "sciences": { "cours": [], "exercices": [], "fiches": [], "qcm": [], "tp": [] }
    }
  },
  {
    "id": "1mvm",
    "short": "Première MVM",
    "full": "Première Bac Pro - Maintenance des Véhicules option Motocycles",
    "niveau": "premiere",
    "filiere": "maintenance",
    "effectif": 10,
    "annee": "Première",
    "couleur": "#10b981",
    "description": "Motos et deux-roues : géométrie, électricité, thermique.",
    "resources": {
      "maths": {
        "cours": [
          { "id": 40, "titre": "Angles et géométrie du châssis moto", "type": "Cours", "desc": "Chasse, angle de chasse, carrossage", "url": "#", "date": "15/09/2025" }
        ],
        "exercices": [
          { "id": 41, "titre": "TD - Calculs de puissance moteur", "type": "Exercices", "desc": "Exercices sur couple et puissance", "url": "#", "date": "08/10/2025" }
        ],
        "fiches": [],
        "qcm": [],
        "tp": [
          { "id": 42, "titre": "TP Diagnostic électrique moto", "type": "TP", "desc": "Fiche de procédure + mesures", "url": "#", "date": "12/12/2025" }
        ]
      },
      "sciences": { "cours": [], "exercices": [], "fiches": [], "qcm": [], "tp": [] }
    }
  },
  {
    "id": "tmvm",
    "short": "Terminale MVM",
    "full": "Terminale Bac Pro - Maintenance des Véhicules option Motocycles",
    "niveau": "terminale",
    "filiere": "maintenance",
    "effectif": 10,
    "annee": "Terminale",
    "couleur": "#10b981",
    "description": "Niveau expert : diagnostic, calculs avancés, réglementation.",
    "resources": {
      "maths": {
        "cours": [
          { "id": 50, "titre": "Diagnostic électronique et OBD", "type": "Cours", "desc": "Lecture de paramètres et codes défauts", "url": "#", "date": "10/09/2025" }
        ],
        "exercices": [],
        "fiches": [
          { "id": 51, "titre": "Fiche révision - Épreuve E3", "type": "Fiche", "desc": "Points essentiels pour l'examen", "url": "#", "date": "18/01/2026" }
        ],
        "qcm": [
          { "id": 52, "titre": "Annales corrigées - Bac Pro MVM", "type": "QCM", "desc": "Session 2024 + 2025", "url": "#", "date": "05/01/2026" }
        ],
        "tp": []
      },
      "sciences": { "cours": [], "exercices": [], "fiches": [], "qcm": [], "tp": [] }
    }
  },
  {
    "id": "1mmev",
    "short": "Première MMEV",
    "full": "Première Bac Pro - Maintenance de Matériels Espaces Verts",
    "niveau": "premiere",
    "filiere": "maintenance",
    "effectif": 10,
    "annee": "Première",
    "couleur": "#059669",
    "description": "Matériels de travaux publics et espaces verts.",
    "resources": {
      "maths": {
        "cours": [
          { "id": 60, "titre": "Hydraulique - Notions de base", "type": "Cours", "desc": "Pression, débit, vérins", "url": "#", "date": "18/09/2025" }
        ],
        "exercices": [
          { "id": 61, "titre": "TD Hydraulique appliquée", "type": "Exercices", "desc": "Exercices de dimensionnement", "url": "#", "date": "07/10/2025" }
        ],
        "fiches": [],
        "qcm": [],
        "tp": []
      },
      "sciences": { "cours": [], "exercices": [], "fiches": [], "qcm": [], "tp": [] }
    }
  },
  {
    "id": "tmmev",
    "short": "Terminale MMEV",
    "full": "Terminale Bac Pro - Maintenance de Matériels Espaces Verts",
    "niveau": "terminale",
    "filiere": "maintenance",
    "effectif": 10,
    "annee": "Terminale",
    "couleur": "#059669",
    "description": "Maintenance avancée des engins d'espaces verts.",
    "resources": {
      "maths": {
        "cours": [],
        "exercices": [],
        "fiches": [
          { "id": 70, "titre": "Fiche révision Bac Pro - MMEV", "type": "Fiche", "desc": "Maths et sciences pour l'examen", "url": "#", "date": "20/01/2026" }
        ],
        "qcm": [],
        "tp": []
      },
      "sciences": { "cours": [], "exercices": [], "fiches": [], "qcm": [], "tp": [] }
    }
  },
  {
    "id": "2mp3d",
    "short": "Seconde MP3D",
    "full": "Seconde Bac Pro - Modélisation et Prototypage 3D",
    "niveau": "seconde",
    "filiere": "modelisation",
    "effectif": 12,
    "annee": "Seconde",
    "couleur": "#7c3aed",
    "description": "Mathématiques pour la modélisation et l'impression 3D.",
    "resources": {
      "maths": {
        "cours": [
          { "id": 801, "titre": "Géométrie dans l'espace et projections", "type": "Cours", "desc": "Vues, coupes, développés", "url": "#", "date": "16/09/2025" },
          { "id": 802, "titre": "Fonctions et courbes paramétriques", "type": "Cours", "desc": "Modélisation de formes", "url": "#", "date": "30/09/2025" }
        ],
        "exercices": [
          { "id": 803, "titre": "TD Modélisation 3D - Volumes", "type": "Exercices", "desc": "Calculs et représentation", "url": "#", "date": "14/10/2025" }
        ],
        "fiches": [
          { "id": 804, "titre": "Raccourcis et astuces Fusion 360", "type": "Fiche", "desc": "Aide-mémoire modélisation", "url": "#", "date": "22/01/2026" }
        ],
        "qcm": [],
        "tp": [
          { "id": 805, "titre": "Projet : Modélisation d'une pièce mécanique", "type": "TP", "desc": "Consigne complète + grille", "url": "#", "date": "05/12/2025" }
        ]
      },
      "sciences": { "cours": [], "exercices": [], "fiches": [], "qcm": [], "tp": [] }
    }
  },
  {
    "id": "1mp3d",
    "short": "Première MP3D",
    "full": "Première Bac Pro - Modélisation et Prototypage 3D",
    "niveau": "premiere",
    "filiere": "modelisation",
    "effectif": 15,
    "annee": "Première",
    "couleur": "#7c3aed",
    "description": "Approfondissement CAO et calculs de résistance.",
    "resources": {
      "maths": {
        "cours": [
          { "id": 90, "titre": "Nombres complexes et rotation 3D", "type": "Cours", "desc": "Application à la modélisation", "url": "#", "date": "12/09/2025" }
        ],
        "exercices": [
          { "id": 91, "titre": "TD - Maillage et optimisation", "type": "Exercices", "desc": "Exercices de calculs de surfaces", "url": "#", "date": "21/10/2025" }
        ],
        "fiches": [],
        "qcm": [],
        "tp": []
      },
      "sciences": { "cours": [], "exercices": [], "fiches": [], "qcm": [], "tp": [] }
    }
  },
  {
    "id": "tmp3d",
    "short": "Terminale MP3D",
    "full": "Terminale Bac Pro - Modélisation et Prototypage 3D",
    "niveau": "terminale",
    "filiere": "modelisation",
    "effectif": 12,
    "annee": "Terminale",
    "couleur": "#7c3aed",
    "description": "Niveau avancé : simulation, prototypage et dossier technique.",
    "resources": {
      "maths": {
        "cours": [],
        "exercices": [],
        "fiches": [
          { "id": 100, "titre": "Fiche révision - Épreuve maths/sciences", "type": "Fiche", "desc": "Points clés Terminale MP3D", "url": "#", "date": "15/01/2026" }
        ],
        "qcm": [],
        "tp": []
      },
      "sciences": { "cours": [], "exercices": [], "fiches": [], "qcm": [], "tp": [] }
    }
  },
  {
    "id": "2mtne",
    "short": "Seconde MTNE",
    "full": "Seconde Bac Pro - Métiers des Transitions Numériques et Énergétiques",
    "niveau": "seconde",
    "filiere": "electrique",
    "effectif": 27,
    "annee": "Seconde",
    "couleur": "#0ea5e9",
    "description": "Transition énergétique, numérique et bases scientifiques.",
    "resources": {
      "maths": {
        "cours": [
          { "id": 110, "titre": "Énergie et puissance électrique", "type": "Cours", "desc": "Bilan énergétique et rendement", "url": "#", "date": "17/09/2025" },
          { "id": 111, "titre": "Fonctions et modélisation de phénomènes", "type": "Cours", "desc": "Croissance, évolution", "url": "#", "date": "01/10/2025" }
        ],
        "exercices": [
          { "id": 112, "titre": "TD - Consommation et facturation électrique", "type": "Exercices", "desc": "Exercices concrets", "url": "#", "date": "08/10/2025" }
        ],
        "fiches": [],
        "qcm": [],
        "tp": []
      },
      "sciences": { "cours": [], "exercices": [], "fiches": [], "qcm": [], "tp": [] }
    }
  },
  {
    "id": "1melec",
    "short": "Première MELEC",
    "full": "Première Bac Pro - Métiers de l'Électricité et ses Environnements Connectés",
    "niveau": "premiere",
    "filiere": "electrique",
    "effectif": 27,
    "annee": "Première",
    "couleur": "#f59e0b",
    "description": "Électricité, automatismes et réseaux connectés.",
    "resources": {
      "maths": {
        "cours": [
          { "id": 1201, "titre": "Nombres complexes en électrotechnique", "type": "Cours", "desc": "Impédance et diagrammes de Fresnel", "url": "#", "date": "06/10/2025" }
        ],
        "exercices": [
          { "id": 1202, "titre": "TD Circuits RL - RC - RLC", "type": "Exercices", "desc": "12 exercices corrigés", "url": "#", "date": "14/10/2025" }
        ],
        "fiches": [],
        "qcm": [],
        "tp": []
      },
      "sciences": {
        "cours": [
          { "id": 1203, "titre": "Courant alternatif et déphasage", "type": "Cours", "desc": "Sinusoïdes, valeur efficace", "url": "#", "date": "15/09/2025" }
        ],
        "exercices": [],
        "fiches": [
          { "id": 1204, "titre": "Formulaire Électrotechnique", "type": "Fiche", "desc": "Impédances, puissances, Q", "url": "#", "date": "28/01/2026" }
        ],
        "qcm": [],
        "tp": []
      }
    }
  },
  {
    "id": "tmelec",
    "short": "Terminale MELEC",
    "full": "Terminale Bac Pro - Métiers de l'Électricité et ses Environnements Connectés",
    "niveau": "terminale",
    "filiere": "electrique",
    "effectif": 24,
    "annee": "Terminale",
    "couleur": "#f59e0b",
    "description": "Automatismes, domotique, énergie et réseaux intelligents.",
    "resources": {
      "maths": {
        "cours": [
          { "id": 1301, "titre": "Nombres complexes et circuits AC", "type": "Cours", "desc": "Impédance, diagrammes de Fresnel", "url": "#", "date": "10/09/2025" }
        ],
        "exercices": [
          { "id": 1302, "titre": "TD - Calculs d'impédance et puissance", "type": "Exercices", "desc": "15 exercices corrigés", "url": "#", "date": "22/10/2025" }
        ],
        "fiches": [],
        "qcm": [],
        "tp": []
      },
      "sciences": {
        "cours": [
          { "id": 1303, "titre": "Automatismes et langage ladder", "type": "Cours", "desc": "Bases de la programmation d'automates", "url": "#", "date": "12/09/2025" }
        ],
        "exercices": [],
        "fiches": [
          { "id": 1304, "titre": "Fiche révision Bac Pro MELEC", "type": "Fiche", "desc": "Maths et physique pour l'examen", "url": "#", "date": "25/01/2026" }
        ],
        "qcm": [
          { "id": 1305, "titre": "Quiz - Électrotechnique avancée", "type": "QCM", "desc": "20 questions", "url": "#", "date": "19/01/2026" }
        ],
        "tp": [
          { "id": 1306, "titre": "Site Interactif Complet : Induction Électromagnétique", "type": "Site Interactif", "desc": "Simulations 3D, quiz, expériences virtuelles (Faraday & Lenz)", "url": "induction-electromagnetique-tmelec.html", "date": "04/02/2026" },
          { "id": 1307, "titre": "Induction Électromagnétique - Version en ligne (GitHub Pages)", "type": "Ressource en ligne", "desc": "Version complète hébergée avec animations 3D", "url": "https://kande-b.github.io/bacpro-Induction-Electromagnetique/", "date": "04/02/2026" }
        ]
      }
    }
  },
  {
    "id": "2remi",
    "short": "Seconde REMI",
    "full": "Seconde Bac Pro - Réalisation d'Ensembles Mécaniques et Industriels",
    "niveau": "seconde",
    "filiere": "mecanique",
    "effectif": 36,
    "annee": "Seconde",
    "couleur": "#e11d48",
    "description": "Deux divisions. Mécanique de précision et usinage.",
    "resources": {
      "maths": {
        "cours": [
          { "id": 140, "titre": "Lecture de plans et cotation", "type": "Cours", "desc": "Interprétation de dessins industriels", "url": "#", "date": "10/09/2025" },
          { "id": 141, "titre": "Trigonométrie et géométrie dans l'atelier", "type": "Cours", "desc": "Applications directes usinage", "url": "#", "date": "24/09/2025" }
        ],
        "exercices": [
          { "id": 142, "titre": "TD - Calculs d'usinage et vitesses", "type": "Exercices", "desc": "20 exercices corrigés", "url": "#", "date": "01/10/2025" }
        ],
        "fiches": [],
        "qcm": [],
        "tp": []
      },
      "sciences": { "cours": [], "exercices": [], "fiches": [], "qcm": [], "tp": [] }
    }
  },
  {
    "id": "1tci",
    "short": "Première TCI",
    "full": "Première Bac Pro - Technicien Chaudronnerie Industrielle",
    "niveau": "premiere",
    "filiere": "chaudronnerie",
    "effectif": 36,
    "annee": "Première",
    "couleur": "#ea580c",
    "description": "Deux divisions. Chaudronnerie industrielle avancée.",
    "resources": {
      "maths": {
        "cours": [
          { "id": 150, "titre": "Calcul des développés complexes", "type": "Cours", "desc": "Pièces à double courbure", "url": "#", "date": "18/09/2025" },
          { "id": 151, "titre": "RDM - Notions avancées", "type": "Cours", "desc": "Flexion et torsion", "url": "#", "date": "09/10/2025" }
        ],
        "exercices": [
          { "id": 152, "titre": "TD Chaudronnerie - Projets réels", "type": "Exercices", "desc": "Exercices d'entreprise", "url": "#", "date": "15/10/2025" }
        ],
        "fiches": [
          { "id": 153, "titre": "Formulaire Chaudronnerie Industrielle", "type": "Fiche", "desc": "Tout le programme Première", "url": "#", "date": "27/01/2026" }
        ],
        "qcm": [],
        "tp": []
      },
      "sciences": { "cours": [], "exercices": [], "fiches": [], "qcm": [], "tp": [] }
    }
  },
  {
    "id": "ttci",
    "short": "Terminale TCI",
    "full": "Terminale Bac Pro - Technicien Chaudronnerie Industrielle",
    "niveau": "terminale",
    "filiere": "chaudronnerie",
    "effectif": 24,
    "annee": "Terminale",
    "couleur": "#ea580c",
    "description": "Niveau technicien : dossiers de fabrication et contrôle.",
    "resources": {
      "maths": {
        "cours": [],
        "exercices": [],
        "fiches": [
          { "id": 160, "titre": "Fiche révision - Bac Pro TCI", "type": "Fiche", "desc": "Maths & sciences - Terminale", "url": "#", "date": "14/01/2026" }
        ],
        "qcm": [],
        "tp": [
          { "id": 161, "titre": "Dossier technique - Exemple complet", "type": "TP", "desc": "Projet de fin d'études", "url": "#", "date": "08/01/2026" }
        ]
      },
      "sciences": { "cours": [], "exercices": [], "fiches": [], "qcm": [], "tp": [] }
    }
  },
  {
    "id": "csta",
    "short": "CSTA - Technicien Ascensoriste",
    "full": "Certification de Spécialisation - Technicien Ascensoriste",
    "niveau": "postbac",
    "filiere": "maintenance",
    "effectif": 12,
    "annee": "CS 1 an",
    "couleur": "#14b8a6",
    "description": "Formation intensive post-Bac Pro.",
    "resources": {
      "maths": {
        "cours": [
          { "id": 170, "titre": "Maths appliquées aux ascenseurs", "type": "Cours", "desc": "Vitesse, accélération, sécurité", "url": "#", "date": "09/09/2025" }
        ],
        "exercices": [],
        "fiches": [],
        "qcm": [],
        "tp": []
      },
      "sciences": { "cours": [], "exercices": [], "fiches": [], "qcm": [], "tp": [] }
    }
  },
  {
    "id": "cstt",
    "short": "CSTT - Technicien en Tuyauterie",
    "full": "Certification de Spécialisation - Technicien en Tuyauterie",
    "niveau": "postbac",
    "filiere": "chaudronnerie",
    "effectif": 12,
    "annee": "CS 1 an",
    "couleur": "#14b8a6",
    "description": "Tuyauterie industrielle et soudure.",
    "resources": {
      "maths": {
        "cours": [],
        "exercices": [],
        "fiches": [
          { "id": 180, "titre": "Fiche - Calculs de tuyauterie", "type": "Fiche", "desc": "Débits, pertes de charge", "url": "#", "date": "16/01/2026" }
        ],
        "qcm": [],
        "tp": []
      },
      "sciences": { "cours": [], "exercices": [], "fiches": [], "qcm": [], "tp": [] }
    }
  },
  {
    "id": "csmiop",
    "short": "CSMIOP - Maintenance Oléo-Hydraulique",
    "full": "CS - Maintenance des Installations Oléo-Hydrauliques et Pneumatiques",
    "niveau": "postbac",
    "filiere": "maintenance",
    "effectif": 12,
    "annee": "CS 1 an",
    "couleur": "#14b8a6",
    "description": "Hydraulique et pneumatique industrielles.",
    "resources": {
      "maths": {
        "cours": [
          { "id": 190, "titre": "Hydraulique proportionnelle", "type": "Cours", "desc": "Régulation et asservissement", "url": "#", "date": "22/09/2025" }
        ],
        "exercices": [],
        "fiches": [],
        "qcm": [],
        "tp": []
      },
      "sciences": { "cours": [], "exercices": [], "fiches": [], "qcm": [], "tp": [] }
    }
  },
  {
    "id": "fcil-mb",
    "short": "FCIL Mobilité Urbaine",
    "full": "Formation Complémentaire d'Initiative Locale - Mobilité Urbaine",
    "niveau": "postbac",
    "filiere": "maintenance",
    "effectif": 12,
    "annee": "FCIL 1 an",
    "couleur": "#14b8a6",
    "description": "Mobilité électrique et nouvelles technologies urbaines.",
    "resources": {
      "maths": { "cours": [], "exercices": [], "fiches": [], "qcm": [], "tp": [] },
      "sciences": { "cours": [], "exercices": [], "fiches": [], "qcm": [], "tp": [] }
    }
  },
  {
    "id": "bts-cri1",
    "short": "BTS CRI 1ère année",
    "full": "BTS Conception et Réalisation en Chaudronnerie Industrielle (GRETA)",
    "niveau": "bts",
    "filiere": "bts",
    "effectif": 12,
    "annee": "BTS 1ère année",
    "couleur": "#475569",
    "description": "Niveau technicien supérieur en alternance.",
    "resources": {
      "maths": {
        "cours": [
          { "id": 200, "titre": "Résistance des matériaux - Niveau BTS", "type": "Cours", "desc": "Flexion composée, flambement", "url": "#", "date": "10/09/2025" },
          { "id": 201, "titre": "Calculs de structures soudées", "type": "Cours", "desc": "Normes et dimensionnement", "url": "#", "date": "01/10/2025" }
        ],
        "exercices": [
          { "id": 202, "titre": "TD RDM - BTS CRI", "type": "Exercices", "desc": "Série complète corrigée", "url": "#", "date": "15/10/2025" }
        ],
        "fiches": [],
        "qcm": [],
        "tp": []
      },
      "sciences": { "cours": [], "exercices": [], "fiches": [], "qcm": [], "tp": [] }
    }
  },
  {
    "id": "bts-cri2",
    "short": "BTS CRI 2ème année",
    "full": "BTS Conception et Réalisation en Chaudronnerie Industrielle (GRETA)",
    "niveau": "bts",
    "filiere": "bts",
    "effectif": 12,
    "annee": "BTS 2ème année",
    "couleur": "#475569",
    "description": "Approfondissement et projet de fin d'études.",
    "resources": {
      "maths": {
        "cours": [],
        "exercices": [],
        "fiches": [
          { "id": 210, "titre": "Fiche révision - BTS CRI", "type": "Fiche", "desc": "Maths et sciences pour les partiels", "url": "#", "date": "12/01/2026" }
        ],
        "qcm": [],
        "tp": []
      },
      "sciences": { "cours": [], "exercices": [], "fiches": [], "qcm": [], "tp": [] }
    }
  },
  {
    "id": "bts-elt1",
    "short": "BTS Electrotechnique 1ère année",
    "full": "BTS Electrotechnique par alternance (GRETA)",
    "niveau": "bts",
    "filiere": "bts",
    "effectif": 12,
    "annee": "BTS 1ère année",
    "couleur": "#475569",
    "description": "Niveau supérieur en électrotechnique.",
    "resources": {
      "maths": {
        "cours": [
          { "id": 220, "titre": "Électrotechnique - Machines tournantes", "type": "Cours", "desc": "Moteurs asynchrones et synchrones", "url": "#", "date": "18/09/2025" }
        ],
        "exercices": [
          { "id": 221, "titre": "TD - Bilans de puissance et rendement", "type": "Exercices", "desc": "Exercices de BTS", "url": "#", "date": "14/10/2025" }
        ],
        "fiches": [],
        "qcm": [],
        "tp": []
      },
      "sciences": { "cours": [], "exercices": [], "fiches": [], "qcm": [], "tp": [] }
    }
  },
  {
    "id": "bts-elt2",
    "short": "BTS Electrotechnique 2ème année",
    "full": "BTS Electrotechnique par alternance (GRETA)",
    "niveau": "bts",
    "filiere": "bts",
    "effectif": 24,
    "annee": "BTS 2ème année",
    "couleur": "#475569",
    "description": "Projet industriel et soutenance.",
    "resources": {
      "maths": {
        "cours": [],
        "exercices": [],
        "fiches": [
          { "id": 230, "titre": "Fiche révision finale - BTS Electrotechnique", "type": "Fiche", "desc": "Mathématiques et physique appliquées", "url": "#", "date": "20/01/2026" }
        ],
        "qcm": [],
        "tp": []
      },
      "sciences": { "cours": [], "exercices": [], "fiches": [], "qcm": [], "tp": [] }
    }
  }
]
